django_celery_extensions/__init__.py
django_celery_extensions/apps.py
django_celery_extensions/beat.py
django_celery_extensions/celery.py
django_celery_extensions/checks.py
django_celery_extensions/config.py
django_celery_extensions/task.py
django_celery_extensions/bin/__init__.py
django_celery_extensions/bin/celeryautoreload.py
example/__init__.py
example/manage.py
example/urls.py
example/wsgi.py
example/app/__init__.py
example/app/models.py
example/app/tasks.py
example/app/tests.py
example/app/management/__init__.py
example/app/management/commands/__init__.py
example/app/management/commands/create_user.py
example/settings/__init__.py
example/settings/celery.py
example/settings/settings.py
skip_django_celery_extensions-1.0.0.dist-info/AUTHORS.rst
skip_django_celery_extensions-1.0.0.dist-info/LICENSE
skip_django_celery_extensions-1.0.0.dist-info/METADATA
skip_django_celery_extensions-1.0.0.dist-info/WHEEL
skip_django_celery_extensions-1.0.0.dist-info/entry_points.txt
skip_django_celery_extensions-1.0.0.dist-info/top_level.txt
skip_django_celery_extensions-1.0.0.dist-info/RECORD
