Metadata-Version: 2.1
Name: skip-django-celery-extensions
Version: 1.0.0
Summary: Django celery extensions library.
Home-page: https://github.com/skip-pay/django-celery-extensions
Author: Lubos Matl
Author-email: matllubos@gmail.com
License: MIT
Keywords: django,celery
Classifier: Development Status :: 3 - Alpha
Classifier: Environment :: Web Environment
Classifier: Framework :: Django
Classifier: Intended Audience :: Developers
Classifier: Intended Audience :: End Users/Desktop
Classifier: License :: OSI Approved :: MIT License
Classifier: Natural Language :: Czech
Classifier: Operating System :: OS Independent
Classifier: Programming Language :: Python
Classifier: Topic :: Internet :: WWW/HTTP :: Dynamic Content
Classifier: Topic :: Internet :: WWW/HTTP :: Site Management
License-File: LICENSE
License-File: AUTHORS.rst
Requires-Dist: django >=4.2.0
Requires-Dist: import-string >=0.1.0
Requires-Dist: celery <5.4,>=5.2
